PySys-2.2.data/scripts/pysys.py
pysys/__init__.py
pysys/__main__.py
pysys/baserunner.py
pysys/basetest.py
pysys/constants.py
pysys/exceptions.py
pysys/mappers.py
pysys/config/__init__.py
pysys/config/descriptor.py
pysys/config/manual.py
pysys/config/project.py
pysys/config/templates/pysysignore
pysys/config/templates/default-test/pysystest.py
pysys/config/templates/dirconfig/pysysdirconfig.xml
pysys/config/templates/project/default.xml
pysys/config/templates/pysystest-xml-test/pysystest.xml
pysys/config/templates/pysystest-xml-test/run.py
pysys/internal/__init__.py
pysys/internal/initlogging.py
pysys/launcher/__init__.py
pysys/launcher/console.py
pysys/launcher/console_clean.py
pysys/launcher/console_make.py
pysys/launcher/console_makeproject.py
pysys/launcher/console_print.py
pysys/launcher/console_run.py
pysys/manual/__init__.py
pysys/manual/ui.py
pysys/perf/__init__.py
pysys/perf/api.py
pysys/perf/perfreportstool.py
pysys/perf/reporters.py
pysys/process/__init__.py
pysys/process/commonwrapper.py
pysys/process/monitor.py
pysys/process/monitorimpl.py
pysys/process/user.py
pysys/process/plat-unix/helper.py
pysys/process/plat-win32/helper.py
pysys/unit/__init__.py
pysys/unit/pyunit.py
pysys/utils/__init__.py
pysys/utils/allocport.py
pysys/utils/filecopy.py
pysys/utils/filediff.py
pysys/utils/filegrep.py
pysys/utils/filereplace.py
pysys/utils/fileunzip.py
pysys/utils/fileutils.py
pysys/utils/linecount.py
pysys/utils/logutils.py
pysys/utils/misc.py
pysys/utils/osutils.py
pysys/utils/perfreporter.py
pysys/utils/pycompat.py
pysys/utils/safeeval.py
pysys/utils/stringutils.py
pysys/utils/threadpool.py
pysys/utils/threadutils.py
pysys/writer/__init__.py
pysys/writer/api.py
pysys/writer/ci.py
pysys/writer/console.py
pysys/writer/coverage.py
pysys/writer/outcomes.py
pysys/writer/testoutput.py
pysys/xml/__init__.py
pysys/xml/descriptor.py
pysys/xml/manual.py
pysys/xml/project.py
PySys-2.2.dist-info/BaseTest.rst
PySys-2.2.dist-info/CHANGELOG.rst
PySys-2.2.dist-info/LICENSE.txt
PySys-2.2.dist-info/METADATA
PySys-2.2.dist-info/ProjectConfiguration.rst
PySys-2.2.dist-info/README.rst
PySys-2.2.dist-info/TestDescriptors.rst
PySys-2.2.dist-info/UserGuide.rst
PySys-2.2.dist-info/WHEEL
PySys-2.2.dist-info/top_level.txt
PySys-2.2.dist-info/RECORD
