Metadata-Version: 2.1
Name: PySys
Version: 2.2
Summary: Python System Test Framework
Home-page: https://pysys-test.github.io/pysys-test
Author: Moray Grieve, Ben Spiller
Author-email: pysys-dev@googlegroups.com
Maintainer: Ben Spiller
Maintainer-email: pysys-dev@googlegroups.com
License: GNU Lesser General Public License
Project-URL: Repository, https://github.com/pysys-test/pysys-test
Project-URL: Tracker, https://github.com/pysys-test/pysys-test/issues
Project-URL: Change Log, https://pysys-test.github.io/pysys-test/ChangeLog.html
Project-URL: Sample, https://github.com/pysys-test/sample-getting-started
Project-URL: Ask a Question, https://stackoverflow.com/questions/ask?tags=pysys
Keywords: testing,qa,system testing,integration testing,unit testing
Platform: Operating System :: Microsoft :: Windows
Platform: Operating System :: POSIX :: Linux
Platform: Operating System :: OS Independent
Platform: Operating System :: MacOS
Classifier: License :: OSI Approved :: GNU Lesser General Public License v2 (LGPLv2)
Classifier: Development Status :: 5 - Production/Stable
Classifier: Intended Audience :: Developers
Classifier: Programming Language :: Python
Classifier: Programming Language :: Python :: 3
Classifier: Programming Language :: Python :: 3.8
Classifier: Programming Language :: Python :: 3.9
Classifier: Programming Language :: Python :: 3.10
Classifier: Programming Language :: Python :: 3.11
Classifier: Programming Language :: Python :: 3.12
Classifier: Programming Language :: Python :: Implementation :: CPython
Classifier: Environment :: Console
Classifier: Topic :: Software Development :: Quality Assurance
Classifier: Topic :: Software Development :: Testing
Classifier: Topic :: Education :: Testing
Classifier: Intended Audience :: Developers
Classifier: Intended Audience :: Education
Classifier: Natural Language :: English
Classifier: Operating System :: Microsoft :: Windows
Classifier: Operating System :: POSIX :: Linux
Classifier: Operating System :: OS Independent
Classifier: Operating System :: MacOS
Requires-Python: >=3, <4
License-File: LICENSE.txt
License-File: README.rst
License-File: CHANGELOG.rst
License-File: docs/pysys/UserGuide.rst
License-File: docs/pysys/BaseTest.rst
License-File: docs/pysys/ProjectConfiguration.rst
License-File: docs/pysys/TestDescriptors.rst
Requires-Dist: pywin32 ; sys_platform == "win32"
Requires-Dist: colorama ; sys_platform == "win32"
